zebracat_monitoring_client/__init__.py
zebracat_monitoring_client/__main__.py
zebracat_monitoring_client/client.py
zebracat_monitoring_client-0.0.6.dist-info/METADATA
zebracat_monitoring_client-0.0.6.dist-info/WHEEL
zebracat_monitoring_client-0.0.6.dist-info/licenses/LICENSE
zebracat_monitoring_client-0.0.6.dist-info/RECORD
